AlloyFrame/AlloyFrame.py
AlloyFrame/LoadFrame.py
AlloyFrame/Methods.py
AlloyFrame/__init__.py
AlloyFrame/__main__.py
AlloyFrame/featurize.py
elecomb/__init__.py
elecomb/__main__.py
elecomb/elecomb_.c
elecomb/elecomb_.cp310-win_amd64.pyd
elecomb/elecomb_.cp313-win_amd64.pyd
elecomb/elecomb_.cpp
elecomb/elecomb_.cpython-310-x86_64-linux-gnu.so
elecomb/elecomb_.pyx
elecomb/elecomb_i.c
elecomb/elecomb_i.cpp
elecomb/elecombp.py
features/__init__.py
features/__main__.py
features/calculate.py
alloyframe-0.3.0.dist-info/METADATA
alloyframe-0.3.0.dist-info/WHEEL
alloyframe-0.3.0.dist-info/top_level.txt
alloyframe-0.3.0.dist-info/RECORD
