Metadata-Version: 2.4
Name: AlloyFrame
Version: 0.3.0
Summary: A framework for alloy analysis and feature extraction
Author: FuHuaShangXian
License: MIT
Project-URL: Homepage, https://gitee.com/taixushangxian/alloy-frame
Project-URL: Repository, https://gitee.com/taixushangxian/alloy-frame.git
Classifier: Development Status :: 3 - Alpha
Classifier: Intended Audience :: Science/Research
Classifier: License :: OSI Approved :: MIT License
Classifier: Programming Language :: Python :: 3
Classifier: Programming Language :: Python :: 3.8
Classifier: Programming Language :: Python :: 3.9
Classifier: Programming Language :: Python :: 3.10
Classifier: Programming Language :: Python :: 3.11
Classifier: Programming Language :: Python :: 3.12
Requires-Python: >=3.8
Requires-Dist: pandas
Requires-Dist: pymatgen
Requires-Dist: numpy
Requires-Dist: tqdm
Requires-Dist: periodictable
